setun70.py
setun70-1.1.0.dist-info/licenses/LICENSE
setun70-1.1.0.dist-info/METADATA
setun70-1.1.0.dist-info/WHEEL
setun70-1.1.0.dist-info/entry_points.txt
setun70-1.1.0.dist-info/top_level.txt
setun70-1.1.0.dist-info/RECORD
