Metadata-Version: 2.4
Name: setun70
Version: 1.1.0
Summary: A working emulator of the Soviet Setun 70 ternary computer (1970)
Author-email: The Ian Index <zaneham@users.noreply.github.com>
License: MIT
Project-URL: Homepage, https://github.com/Zaneham/setun70-emulator
Project-URL: Documentation, https://github.com/Zaneham/setun70-emulator#readme
Project-URL: Repository, https://github.com/Zaneham/setun70-emulator
Project-URL: Issues, https://github.com/Zaneham/setun70-emulator/issues
Keywords: emulator,ternary,computer,soviet,setun,history,retrocomputing,balanced-ternary,stack-machine,POLIZ
Classifier: Development Status :: 4 - Beta
Classifier: Intended Audience :: Developers
Classifier: Intended Audience :: Education
Classifier: Intended Audience :: Science/Research
Classifier: License :: OSI Approved :: MIT License
Classifier: Operating System :: OS Independent
Classifier: Programming Language :: Python :: 3
Classifier: Programming Language :: Python :: 3.10
Classifier: Programming Language :: Python :: 3.11
Classifier: Programming Language :: Python :: 3.12
Classifier: Topic :: Education
Classifier: Topic :: Scientific/Engineering
Classifier: Topic :: Software Development :: Interpreters
Classifier: Topic :: System :: Emulators
Requires-Python: >=3.10
License-File: LICENSE
Provides-Extra: dev
Requires-Dist: pytest>=7.0; extra == "dev"
Requires-Dist: pytest-cov>=4.0; extra == "dev"
Dynamic: license-file
